x2c/__init__.py
x2c/cmd.py
x2c-1.0.0.dist-info/LICENSE
x2c-1.0.0.dist-info/METADATA
x2c-1.0.0.dist-info/WHEEL
x2c-1.0.0.dist-info/entry_points.txt
x2c-1.0.0.dist-info/top_level.txt
x2c-1.0.0.dist-info/RECORD
