Metadata-Version: 2.1
Name: x2c
Version: 1.0.0
Summary: A simple cli app to convert XML files to CSV, with user-defined columns.
Home-page: https://github.com/slonki/x2c
Author: Martin Valter
Author-email: martin@circo.dev
License: GPLv3+
Project-URL: Bug Tracker, https://github.com/slonki/x2c/issues
Platform: UNKNOWN
Classifier: Development Status :: 5 - Production/Stable
Classifier: Intended Audience :: Developers
Classifier: Operating System :: OS Independent
Classifier: Natural Language :: English
Classifier: License :: OSI Approved :: GNU General Public License v3 or later (GPLv3+)
Classifier: Programming Language :: Python :: 3
Classifier: Programming Language :: Python :: 3.7
Requires-Python: >=3
License-File: LICENSE
Requires-Dist: pandas
